pymets/__init__.py
pymets/mets_factory.py
pymets/mets_model.py
pymets/tests/__init__.py
pymets/tests/test_mets_factory.py
pymets/tests/test_mets_model.py
pymets-0.1.0.dist-info/DESCRIPTION.rst
pymets-0.1.0.dist-info/METADATA
pymets-0.1.0.dist-info/RECORD
pymets-0.1.0.dist-info/WHEEL
pymets-0.1.0.dist-info/metadata.json
pymets-0.1.0.dist-info/top_level.txt
