Metadata-Version: 2.0
Name: pymets
Version: 0.1.0
Summary: Python library for building METS XML documents
Home-page: UNKNOWN
Author: Sean Mosely
Author-email: sean.mosely@gmail.com
License: MIT
Download-URL: https://github.com/NLNZDigitalPreservation/pymets/archive/v0.1.0.tar.gz
Platform: UNKNOWN
Requires-Dist: lxml (==3.6.4)
